{
  "id": "ev-adapters-services-risk-106",
  "type": "source_analysis",
  "source_path": "src/services/api/filesApi.ts",
  "summary": "filesApi.ts defines getDefaultApiBaseUrl, logDebugError, logDebug, File, FilesApiConfig, DownloadResult and imports axios, crypto, fs/promises, path, ../../utils/array.js",
  "detail": "",
  "quotes_or_symbols": [
    "getDefaultApiBaseUrl",
    "logDebugError",
    "logDebug",
    "File",
    "FilesApiConfig",
    "DownloadResult"
  ],
  "content": "",
  "key_findings": null,
  "packet_id": "adapters-services-risk",
  "collected_at": "2026-05-28T03:28:41.238Z"
}
